apmcheck/__init__.py
apmcheck/cli.py
apmcheck/detector/__init__.py
apmcheck/detector/go.py
apmcheck/detector/java.py
apmcheck/detector/nodejs.py
apmcheck/detector/python.py
apmcheck/reporter/__init__.py
apmcheck/reporter/exporter.py
apmcheck/reporter/formatter.py
apmcheck/utils/__init__.py
apmcheck/utils/coverage.py
apmcheck/utils/webhook.py
apmcheck-0.1.3.dist-info/licenses/LICENSE
apmcheck-0.1.3.dist-info/METADATA
apmcheck-0.1.3.dist-info/WHEEL
apmcheck-0.1.3.dist-info/entry_points.txt
apmcheck-0.1.3.dist-info/top_level.txt
apmcheck-0.1.3.dist-info/RECORD
