Metadata-Version: 2.4
Name: apmcheck
Version: 0.1.3
Summary: CLI tool to detect APM coverage (Datadog, OpenTelemetry)
Author-email: Matias Salinas <support@fenden.com>
License-Expression: MIT
Requires-Python: >=3.7
License-File: LICENSE
Requires-Dist: click>=8.0.0
Dynamic: license-file
